rsyncrun/__init__.py
rsyncrun/compatible.py
rsyncrun/installer.py
rsyncrun/json_conf_template.py
rsyncrun/rsync_run.py
rsyncrun/shell.py
rsyncrun/steps.py
rsyncrun-1.2.0.data/scripts/rsyncrun
rsyncrun-1.2.0.dist-info/LICENSE
rsyncrun-1.2.0.dist-info/METADATA
rsyncrun-1.2.0.dist-info/WHEEL
rsyncrun-1.2.0.dist-info/top_level.txt
rsyncrun-1.2.0.dist-info/RECORD
