Metadata-Version: 2.1
Name: rsyncrun
Version: 1.2.0
Summary: Rsync your code to server and run.
Home-page: http://github.com/luiti/rsyncrun/
Author: David Chen
Author-email: mvjome@gmail.com
License: MIT
Platform: any
Classifier: Intended Audience :: Developers
Classifier: Operating System :: OS Independent
Classifier: Programming Language :: Python
Requires-Python: >=3.7.6
Requires-Dist: cached-property
